llm_straico.py
llm_straico-0.11.dist-info/METADATA
llm_straico-0.11.dist-info/WHEEL
llm_straico-0.11.dist-info/entry_points.txt
llm_straico-0.11.dist-info/top_level.txt
llm_straico-0.11.dist-info/RECORD
