Metadata-Version: 2.1
Name: llm-straico
Version: 0.11
Requires-Dist: straico
Requires-Dist: llm
